LyScript64/__init__.py
LyScript64-1.0.13.dist-info/LICENSE
LyScript64-1.0.13.dist-info/METADATA
LyScript64-1.0.13.dist-info/WHEEL
LyScript64-1.0.13.dist-info/top_level.txt
LyScript64-1.0.13.dist-info/RECORD
